{
  "abstract": [
    {
      "sentence": "We use the following mathematical notation in this writeup: • Vectors are denoted by boldface lower-case letters such as x ∈ R d .",
      "tokens": [
        "We",
        "use",
        "the",
        "following",
        "mathematical",
        "notation",
        "in",
        "this",
        "writeup",
        ":",
        "•",
        "Vectors",
        "are",
        "denoted",
        "by",
        "boldface",
        "lower-case",
        "letters",
        "such",
        "as",
        "x",
        "∈",
        "R",
        "d",
        "."
      ]
    },
    {
      "sentence": "Coordinates of vectors are denoted by underscore notation x i or regular brackets x(i).",
      "tokens": [
        "Coordinates",
        "of",
        "vectors",
        "are",
        "denoted",
        "by",
        "underscore",
        "notation",
        "x",
        "i",
        "or",
        "regular",
        "brackets",
        "x",
        "(",
        "i",
        ")",
        "."
      ]
    },
    {
      "sentence": "• Matrices are denoted by boldface upper-case letters such as X ∈ R m×n .",
      "tokens": [
        "•",
        "Matrices",
        "are",
        "denoted",
        "by",
        "boldface",
        "upper-case",
        "letters",
        "such",
        "as",
        "X",
        "∈",
        "R",
        "m×n",
        "."
      ]
    },
    {
      "sentence": "Their coordinates by X(i, j), or X ij .",
      "tokens": [
        "Their",
        "coordinates",
        "by",
        "X",
        "(",
        "i",
        ",",
        "j",
        ")",
        ",",
        "or",
        "X",
        "ij",
        "."
      ]
    },
    {
      "sentence": "• Functions are denoted by lower case letters f : R d → R. • The k-th differential of function f is denoted by The gradient is denoted without the superscript, as ∇f .",
      "tokens": [
        "•",
        "Functions",
        "are",
        "denoted",
        "by",
        "lower",
        "case",
        "letters",
        "f",
        ":",
        "R",
        "d",
        "→",
        "R.",
        "•",
        "The",
        "k-th",
        "differential",
        "of",
        "function",
        "f",
        "is",
        "denoted",
        "by",
        "The",
        "gradient",
        "is",
        "denoted",
        "without",
        "the",
        "superscript",
        ",",
        "as",
        "∇f",
        "."
      ]
    },
    {
      "sentence": "• We use the mathcal macro for sets, such as K ⊆ R d .",
      "tokens": [
        "•",
        "We",
        "use",
        "the",
        "mathcal",
        "macro",
        "for",
        "sets",
        ",",
        "such",
        "as",
        "K",
        "⊆",
        "R",
        "d",
        "."
      ]
    },
    {
      "sentence": "• We denote the gradient at point x t as ∇ xt , or simply ∇ t .",
      "tokens": [
        "•",
        "We",
        "denote",
        "the",
        "gradient",
        "at",
        "point",
        "x",
        "t",
        "as",
        "∇",
        "xt",
        ",",
        "or",
        "simply",
        "∇",
        "t",
        "."
      ]
    },
    {
      "sentence": "• We denote the global or local optima of functions by x .",
      "tokens": [
        "•",
        "We",
        "denote",
        "the",
        "global",
        "or",
        "local",
        "optima",
        "of",
        "functions",
        "by",
        "x",
        "."
      ]
    },
    {
      "sentence": "• We denote distance to optimality for iterative algorithms by h t = f (x t ) -f (x ).",
      "tokens": [
        "•",
        "We",
        "denote",
        "distance",
        "to",
        "optimality",
        "for",
        "iterative",
        "algorithms",
        "by",
        "h",
        "t",
        "=",
        "f",
        "(",
        "x",
        "t",
        ")",
        "-f",
        "(",
        "x",
        ")",
        "."
      ]
    },
    {
      "sentence": "• Euclidean distance to optimality is denoted d t = x t -x .",
      "tokens": [
        "•",
        "Euclidean",
        "distance",
        "to",
        "optimality",
        "is",
        "denoted",
        "d",
        "t",
        "=",
        "x",
        "t",
        "-x",
        "."
      ]
    }
  ],
  "introduction": [
    {
      "sentence": "Introduction The topic of this lecture series is the mathematical optimization approach to machine learning.",
      "tokens": [
        "Introduction",
        "The",
        "topic",
        "of",
        "this",
        "lecture",
        "series",
        "is",
        "the",
        "mathematical",
        "optimization",
        "approach",
        "to",
        "machine",
        "learning",
        "."
      ]
    },
    {
      "sentence": "In standard algorithmic theory, the burden of designing an efficient algorithm for solving a problem at hand is on the algorithm designer.",
      "tokens": [
        "In",
        "standard",
        "algorithmic",
        "theory",
        ",",
        "the",
        "burden",
        "of",
        "designing",
        "an",
        "efficient",
        "algorithm",
        "for",
        "solving",
        "a",
        "problem",
        "at",
        "hand",
        "is",
        "on",
        "the",
        "algorithm",
        "designer",
        "."
      ]
    },
    {
      "sentence": "In the decades since in the introduction of computer science, elegant algorithms have been designed for tasks ranging from finding the shortest path in a graph, computing the optimal flow in a network, compressing a computer file containing an image captured by digital camera, and replacing a string in a text document.",
      "tokens": [
        "In",
        "the",
        "decades",
        "since",
        "in",
        "the",
        "introduction",
        "of",
        "computer",
        "science",
        ",",
        "elegant",
        "algorithms",
        "have",
        "been",
        "designed",
        "for",
        "tasks",
        "ranging",
        "from",
        "finding",
        "the",
        "shortest",
        "path",
        "in",
        "a",
        "graph",
        ",",
        "computing",
        "the",
        "optimal",
        "flow",
        "in",
        "a",
        "network",
        ",",
        "compressing",
        "a",
        "computer",
        "file",
        "containing",
        "an",
        "image",
        "captured",
        "by",
        "digital",
        "camera",
        ",",
        "and",
        "replacing",
        "a",
        "string",
        "in",
        "a",
        "text",
        "document",
        "."
      ]
    },
    {
      "sentence": "The design approach, while useful to many tasks, falls short of more complicated problems, such as identifying a particular person in an image in bitmap format, or translating text from English to Hebrew.",
      "tokens": [
        "The",
        "design",
        "approach",
        ",",
        "while",
        "useful",
        "to",
        "many",
        "tasks",
        ",",
        "falls",
        "short",
        "of",
        "more",
        "complicated",
        "problems",
        ",",
        "such",
        "as",
        "identifying",
        "a",
        "particular",
        "person",
        "in",
        "an",
        "image",
        "in",
        "bitmap",
        "format",
        ",",
        "or",
        "translating",
        "text",
        "from",
        "English",
        "to",
        "Hebrew",
        "."
      ]
    },
    {
      "sentence": "There may very well be an elegant algorithm for the above tasks, but the algorithmic design scheme does not scale.",
      "tokens": [
        "There",
        "may",
        "very",
        "well",
        "be",
        "an",
        "elegant",
        "algorithm",
        "for",
        "the",
        "above",
        "tasks",
        ",",
        "but",
        "the",
        "algorithmic",
        "design",
        "scheme",
        "does",
        "not",
        "scale",
        "."
      ]
    },
    {
      "sentence": "As Turing promotes in his paper [83] , it is potentially easier to teach a computer to learn how to solve a task, rather than teaching it the solution for the particular tasks.",
      "tokens": [
        "As",
        "Turing",
        "promotes",
        "in",
        "his",
        "paper",
        "[",
        "83",
        "]",
        ",",
        "it",
        "is",
        "potentially",
        "easier",
        "to",
        "teach",
        "a",
        "computer",
        "to",
        "learn",
        "how",
        "to",
        "solve",
        "a",
        "task",
        ",",
        "rather",
        "than",
        "teaching",
        "it",
        "the",
        "solution",
        "for",
        "the",
        "particular",
        "tasks",
        "."
      ]
    },
    {
      "sentence": "In effect, that's what we do at school, or in this lecture series...",
      "tokens": [
        "In",
        "effect",
        ",",
        "that",
        "'s",
        "what",
        "we",
        "do",
        "at",
        "school",
        ",",
        "or",
        "in",
        "this",
        "lecture",
        "series",
        "..."
      ]
    },
    {
      "sentence": "The machine learning approach to solving problems is to have an automated mechanism for learning an algorithm.",
      "tokens": [
        "The",
        "machine",
        "learning",
        "approach",
        "to",
        "solving",
        "problems",
        "is",
        "to",
        "have",
        "an",
        "automated",
        "mechanism",
        "for",
        "learning",
        "an",
        "algorithm",
        "."
      ]
    },
    {
      "sentence": "Consider the problem of classifying images into two categories: those containing cars and those containing chairs (assuming there are only two types of images in the world).",
      "tokens": [
        "Consider",
        "the",
        "problem",
        "of",
        "classifying",
        "images",
        "into",
        "two",
        "categories",
        ":",
        "those",
        "containing",
        "cars",
        "and",
        "those",
        "containing",
        "chairs",
        "(",
        "assuming",
        "there",
        "are",
        "only",
        "two",
        "types",
        "of",
        "images",
        "in",
        "the",
        "world",
        ")",
        "."
      ]
    },
    {
      "sentence": "In ML we train (teach) a machine to achieve the desired functionality.",
      "tokens": [
        "In",
        "ML",
        "we",
        "train",
        "(",
        "teach",
        ")",
        "a",
        "machine",
        "to",
        "achieve",
        "the",
        "desired",
        "functionality",
        "."
      ]
    },
    {
      "sentence": "The same machine can potentially solve any algorithmic task, and differs from task to task only by a set of parameters that determine the functionality of the machine.",
      "tokens": [
        "The",
        "same",
        "machine",
        "can",
        "potentially",
        "solve",
        "any",
        "algorithmic",
        "task",
        ",",
        "and",
        "differs",
        "from",
        "task",
        "to",
        "task",
        "only",
        "by",
        "a",
        "set",
        "of",
        "parameters",
        "that",
        "determine",
        "the",
        "functionality",
        "of",
        "the",
        "machine",
        "."
      ]
    },
    {
      "sentence": "This is much like the wires in a computer chip determine its functionality.",
      "tokens": [
        "This",
        "is",
        "much",
        "like",
        "the",
        "wires",
        "in",
        "a",
        "computer",
        "chip",
        "determine",
        "its",
        "functionality",
        "."
      ]
    },
    {
      "sentence": "Indeed, one of the most popular machines are artificial neural networks.",
      "tokens": [
        "Indeed",
        ",",
        "one",
        "of",
        "the",
        "most",
        "popular",
        "machines",
        "are",
        "artificial",
        "neural",
        "networks",
        "."
      ]
    },
    {
      "sentence": "The mathematical optimization approach to machine learning is to view the process of machine training as an optimization problem.",
      "tokens": [
        "The",
        "mathematical",
        "optimization",
        "approach",
        "to",
        "machine",
        "learning",
        "is",
        "to",
        "view",
        "the",
        "process",
        "of",
        "machine",
        "training",
        "as",
        "an",
        "optimization",
        "problem",
        "."
      ]
    },
    {
      "sentence": "If we let w ∈ R d be the parameters of our machine (a.k.a.",
      "tokens": [
        "If",
        "we",
        "let",
        "w",
        "∈",
        "R",
        "d",
        "be",
        "the",
        "parameters",
        "of",
        "our",
        "machine",
        "(",
        "a.k.a",
        "."
      ]
    },
    {
      "sentence": "model), that are constrained to be in some set K ⊆ R d , and f the function measuring success in mapping examples to their correct label, then the problem we are interested in is described by the mathematical optimization problem of min w∈K f (w) (1.1) This is the problem that the lecture series focuses on, with particular emphasis on functions that arise in machine learning and have special structure that allows for efficient algorithms.",
      "tokens": [
        "model",
        ")",
        ",",
        "that",
        "are",
        "constrained",
        "to",
        "be",
        "in",
        "some",
        "set",
        "K",
        "⊆",
        "R",
        "d",
        ",",
        "and",
        "f",
        "the",
        "function",
        "measuring",
        "success",
        "in",
        "mapping",
        "examples",
        "to",
        "their",
        "correct",
        "label",
        ",",
        "then",
        "the",
        "problem",
        "we",
        "are",
        "interested",
        "in",
        "is",
        "described",
        "by",
        "the",
        "mathematical",
        "optimization",
        "problem",
        "of",
        "min",
        "w∈K",
        "f",
        "(",
        "w",
        ")",
        "(",
        "1.1",
        ")",
        "This",
        "is",
        "the",
        "problem",
        "that",
        "the",
        "lecture",
        "series",
        "focuses",
        "on",
        ",",
        "with",
        "particular",
        "emphasis",
        "on",
        "functions",
        "that",
        "arise",
        "in",
        "machine",
        "learning",
        "and",
        "have",
        "special",
        "structure",
        "that",
        "allows",
        "for",
        "efficient",
        "algorithms",
        "."
      ]
    }
  ]
}