{
  "title": [
    {
      "sentence": "Julia Language in Machine Learning: Algorithms, Applications, and Open Issues",
      "tokens": [
        "Julia",
        "Language",
        "in",
        "Machine",
        "Learning",
        ":",
        "Algorithms",
        ",",
        "Applications",
        ",",
        "and",
        "Open",
        "Issues"
      ]
    }
  ],
  "abstract": [
    {
      "sentence": "Machine learning is driving development across many fields in science and engineering.",
      "tokens": [
        "Machine",
        "learning",
        "is",
        "driving",
        "development",
        "across",
        "many",
        "fields",
        "in",
        "science",
        "and",
        "engineering",
        "."
      ]
    },
    {
      "sentence": "A simple and efficient programming language could accelerate applications of machine learning in various fields.",
      "tokens": [
        "A",
        "simple",
        "and",
        "efficient",
        "programming",
        "language",
        "could",
        "accelerate",
        "applications",
        "of",
        "machine",
        "learning",
        "in",
        "various",
        "fields",
        "."
      ]
    },
    {
      "sentence": "Currently, the programming languages most commonly used to develop machine learning algorithms include Python, MATLAB, and C/C ++.",
      "tokens": [
        "Currently",
        ",",
        "the",
        "programming",
        "languages",
        "most",
        "commonly",
        "used",
        "to",
        "develop",
        "machine",
        "learning",
        "algorithms",
        "include",
        "Python",
        ",",
        "MATLAB",
        ",",
        "and",
        "C/C",
        "++",
        "."
      ]
    },
    {
      "sentence": "However, none of these languages well balance both efficiency and simplicity.",
      "tokens": [
        "However",
        ",",
        "none",
        "of",
        "these",
        "languages",
        "well",
        "balance",
        "both",
        "efficiency",
        "and",
        "simplicity",
        "."
      ]
    },
    {
      "sentence": "The Julia language is a fast, easy-to-use, and open-source programming language that was originally designed for high-performance computing, which can well balance the efficiency and simplicity.",
      "tokens": [
        "The",
        "Julia",
        "language",
        "is",
        "a",
        "fast",
        ",",
        "easy-to-use",
        ",",
        "and",
        "open-source",
        "programming",
        "language",
        "that",
        "was",
        "originally",
        "designed",
        "for",
        "high-performance",
        "computing",
        ",",
        "which",
        "can",
        "well",
        "balance",
        "the",
        "efficiency",
        "and",
        "simplicity",
        "."
      ]
    },
    {
      "sentence": "This paper summarizes the related research work and developments in the applications of the Julia language in machine learning.",
      "tokens": [
        "This",
        "paper",
        "summarizes",
        "the",
        "related",
        "research",
        "work",
        "and",
        "developments",
        "in",
        "the",
        "applications",
        "of",
        "the",
        "Julia",
        "language",
        "in",
        "machine",
        "learning",
        "."
      ]
    },
    {
      "sentence": "It first surveys the popular machine learning algorithms that are developed in the Julia language.",
      "tokens": [
        "It",
        "first",
        "surveys",
        "the",
        "popular",
        "machine",
        "learning",
        "algorithms",
        "that",
        "are",
        "developed",
        "in",
        "the",
        "Julia",
        "language",
        "."
      ]
    },
    {
      "sentence": "Then, it investigates applications of the machine learning algorithms implemented with the Julia language.",
      "tokens": [
        "Then",
        ",",
        "it",
        "investigates",
        "applications",
        "of",
        "the",
        "machine",
        "learning",
        "algorithms",
        "implemented",
        "with",
        "the",
        "Julia",
        "language",
        "."
      ]
    },
    {
      "sentence": "Finally, it discusses the open issues and the potential future directions that arise in the use of the Julia language in machine learning.",
      "tokens": [
        "Finally",
        ",",
        "it",
        "discusses",
        "the",
        "open",
        "issues",
        "and",
        "the",
        "potential",
        "future",
        "directions",
        "that",
        "arise",
        "in",
        "the",
        "use",
        "of",
        "the",
        "Julia",
        "language",
        "in",
        "machine",
        "learning",
        "."
      ]
    }
  ],
  "introduction": [
    {
      "sentence": "Introduction Machine learning is currently one of the most rapidly growing technical fields, lying at the intersection of computer science and statistics and at the core of artificial intelligence and data science [1, 2, 3, 4] .",
      "tokens": [
        "Introduction",
        "Machine",
        "learning",
        "is",
        "currently",
        "one",
        "of",
        "the",
        "most",
        "rapidly",
        "growing",
        "technical",
        "fields",
        ",",
        "lying",
        "at",
        "the",
        "intersection",
        "of",
        "computer",
        "science",
        "and",
        "statistics",
        "and",
        "at",
        "the",
        "core",
        "of",
        "artificial",
        "intelligence",
        "and",
        "data",
        "science",
        "[",
        "1",
        ",",
        "2",
        ",",
        "3",
        ",",
        "4",
        "]",
        "."
      ]
    },
    {
      "sentence": "Machine learning technology powers many aspects of modern society, from web searches to content filtering on social networks to recommendations on electronic commerce websites.",
      "tokens": [
        "Machine",
        "learning",
        "technology",
        "powers",
        "many",
        "aspects",
        "of",
        "modern",
        "society",
        ",",
        "from",
        "web",
        "searches",
        "to",
        "content",
        "filtering",
        "on",
        "social",
        "networks",
        "to",
        "recommendations",
        "on",
        "electronic",
        "commerce",
        "websites",
        "."
      ]
    },
    {
      "sentence": "Recent advances in machine learning methods promise powerful new tools for practicing scientists.",
      "tokens": [
        "Recent",
        "advances",
        "in",
        "machine",
        "learning",
        "methods",
        "promise",
        "powerful",
        "new",
        "tools",
        "for",
        "practicing",
        "scientists",
        "."
      ]
    },
    {
      "sentence": "Modern machine learning methods are closely related to scientific application [5, 6] ; see Figure 1 .",
      "tokens": [
        "Modern",
        "machine",
        "learning",
        "methods",
        "are",
        "closely",
        "related",
        "to",
        "scientific",
        "application",
        "[",
        "5",
        ",",
        "6",
        "]",
        ";",
        "see",
        "Figure",
        "1",
        "."
      ]
    },
    {
      "sentence": "Python, MATLAB, Go, R, and C/C++ are widely used programming languages in machine learning.",
      "tokens": [
        "Python",
        ",",
        "MATLAB",
        ",",
        "Go",
        ",",
        "R",
        ",",
        "and",
        "C/C++",
        "are",
        "widely",
        "used",
        "programming",
        "languages",
        "in",
        "machine",
        "learning",
        "."
      ]
    }
  ]
}